LICENSE
README.md
README_CN.md
build.py
ctp/__init__.py
ctp/__version__.py
ctp/ctp.h
ctp/api/__init__.py
ctp/api/ctp_constant.py
ctp/api/ctpmd.cp313-win_amd64.pyd
ctp/api/ctpmd.pyi
ctp/api/ctptd.cp313-win_amd64.pyd
ctp/api/ctptd.pyi
ctp/api/custom_constant.py
ctp/api/thostmduserapi_se.dll
ctp/api/thostmduserapi_se.so
ctp/api/thosttraderapi_se.dll
ctp/api/thosttraderapi_se.so
ctp/api/generator/generate_api_functions.py
ctp/api/generator/generate_cpp.py
ctp/api/generator/generate_data_type.py
ctp/api/generator/generate_dll_entry.py
ctp/api/generator/generate_function_const.py
ctp/api/generator/generate_helper.py
ctp/api/generator/generate_onekey.py
ctp/api/generator/generate_struct.py
ctp/api/include/ThostFtdcMdApi.h
ctp/api/include/ThostFtdcTraderApi.h
ctp/api/include/ThostFtdcUserApiDataType.h
ctp/api/include/ThostFtdcUserApiStruct.h
ctp/api/libs/thostmduserapi_se.lib
ctp/api/libs/thosttraderapi_se.lib
ctp/api/src/ctp.h
ctp/api/src/ctpmd/ctpmd.cpp
ctp/api/src/ctpmd/ctpmd.h
ctp/api/src/ctpmd/dllmain.cpp
ctp/api/src/ctpmd/stdafx.cpp
ctp/api/src/ctpmd/stdafx.h
ctp/api/src/ctptd/ctptd.cpp
ctp/api/src/ctptd/ctptd.h
ctp/api/src/ctptd/dllmain.cpp
ctp/api/src/ctptd/stdafx.cpp
ctp/api/src/ctptd/stdafx.h
docs/Disclaimer.md
docs/免责声明.md
hatch_build.py
meson.build
homalos_ctp-6.7.11.4.dist-info/METADATA
homalos_ctp-6.7.11.4.dist-info/WHEEL
homalos_ctp-6.7.11.4.dist-info/licenses/LICENSE
homalos_ctp-6.7.11.4.dist-info/RECORD
