Metadata-Version: 2.4
Name: homalos-ctp
Version: 6.7.11.4
Summary: CTP Python API extension module construction.
Project-URL: Homepage, https://github.com/Homalos/ctp
Project-URL: Repository, https://github.com/Homalos/ctp
Project-URL: Documentation, https://github.com/Homalos/ctp/blob/main/README.md
Project-URL: Issues, https://github.com/Homalos/ctp/issues
Project-URL: Documentation (中文), https://github.com/Homalos/ctp/blob/main/README_CN.md
Author-email: Lumosylva <donnymoving@gmail.com>
License: MIT License
License-File: LICENSE
Keywords: ctp,investment,quantitative,trading
Classifier: Development Status :: 4 - Beta
Classifier: Intended Audience :: Developers
Classifier: License :: OSI Approved :: MIT License
Classifier: Natural Language :: Chinese (Simplified)
Classifier: Operating System :: Microsoft :: Windows
Classifier: Operating System :: POSIX :: Linux
Classifier: Programming Language :: Python :: 3
Classifier: Programming Language :: Python :: 3.10
Classifier: Programming Language :: Python :: 3.11
Classifier: Programming Language :: Python :: 3.12
Classifier: Programming Language :: Python :: 3.13
Classifier: Programming Language :: Python :: Implementation :: CPython
Classifier: Topic :: Office/Business :: Financial :: Investment
Requires-Python: >=3.13
Requires-Dist: hatch>=1.14.1
Requires-Dist: meson-python>=0.18.0
Requires-Dist: pybind11-stubgen>=2.5.5
Requires-Dist: pybind11>=3.0.1
Requires-Dist: twine>=6.1.0
